AlignmentUtilis/BM.py
AlignmentUtilis/KmerIndex.py
AlignmentUtilis/Naive.py
AlignmentUtilis/Pairwise.py
AlignmentUtilis/__init__.py
AlignmentUtilis-0.1.0.dist-info/LICENSE
AlignmentUtilis-0.1.0.dist-info/METADATA
AlignmentUtilis-0.1.0.dist-info/WHEEL
AlignmentUtilis-0.1.0.dist-info/top_level.txt
AlignmentUtilis-0.1.0.dist-info/RECORD
