Metadata-Version: 2.1
Name: AlignmentUtilis
Version: 0.1.0
Summary: Simple application of sequence alignment algorithms
Author-email: Youpu Chen <otis.hongpu@gmail.com>
Classifier: Development Status :: 3 - Alpha
Classifier: Intended Audience :: Information Technology
Classifier: Topic :: Scientific/Engineering :: Bio-Informatics
Classifier: License :: OSI Approved :: MIT License
Classifier: Programming Language :: Python :: 3
Classifier: Programming Language :: Python :: 3.8
Requires-Python: >=3.8
License-File: LICENSE
